LICENCE.txt
MANIFEST.in
README.txt
__init__.py
setup.py
TeraApp/__init__.py
TeraApp/test12121.py
TeraApp.egg-info/PKG-INFO
TeraApp.egg-info/SOURCES.txt
TeraApp.egg-info/dependency_links.txt
TeraApp.egg-info/requires.txt
TeraApp.egg-info/top_level.txt
TeraApp/AppScreen/AppScreen.py
TeraApp/AppScreen/__init__.py
TeraApp/AppScreen/test1.py
TeraApp/Functions/__init__.py
TeraApp/Functions/functions.py