Metadata-Version: 2.1
Name: TeraApp
Version: 0.3.3
Summary: A very simple app creator
Home-page: 
Author: oren
Author-email: orennadle@gmail.com
License: MIT
Keywords: appcreator computerapps exe app apps creator maker appmaker makerapp makerapps creatorapps appscreator
Classifier: Development Status :: 5 - Production/Stable
Classifier: Intended Audience :: Education
Classifier: Operating System :: Microsoft :: Windows :: Windows 10
Classifier: License :: OSI Approved :: MIT License
Classifier: Programming Language :: Python :: 3
License-File: LICENCE.txt
